{
	"info": {
		"_postman_id": "057aaf15-ab81-4225-9d3d-aff00d4e2268",
		"name": "MO3FLEX",
		"schema": "https://schema.getpostman.com/json/collection/v2.1.0/collection.json"
	},
	"item": [
		{
			"name": "User",
			"item": [
				{
					"name": "Sign Up",
					"event": [
						{
							"listen": "test",
							"script": {
								"id": "2361ec84-431c-4acf-9b23-89c369f56e6a",
								"exec": [
									"if(pm.response.code === 201) {",
									"    pm.environment.set('authToken', pm.response.json().token)",
									"}"
								],
								"type": "text/javascript"
							}
						}
					],
					"request": {
						"auth": {
							"type": "noauth"
						},
						"method": "POST",
						"header": [],
						"body": {
							"mode": "raw",
							"raw": "{\n\t\"firstName\": \"sara\",\n\t\"lastName\": \"Salama\",\n\t\"email\": \"sarsssa@yahoo.com\",\n\t\"password\": \"12345ss678\",\n\t\"gender\": \"female\"\n\n\t\n}",
							"options": {
								"raw": {
									"language": "json"
								}
							}
						},
						"url": {
							"raw": "{{url}}/users/signup",
							"host": [
								"{{url}}"
							],
							"path": [
								"users",
								"signup"
							]
						}
					},
					"response": []
				},
				{
					"name": "Log In",
					"event": [
						{
							"listen": "test",
							"script": {
								"id": "92dd778b-4108-4a4f-a08e-490ed78d8227",
								"exec": [
									"if(pm.response.code === 200) {",
									"    pm.environment.set('authToken', pm.response.json().token)",
									"}"
								],
								"type": "text/javascript"
							}
						}
					],
					"request": {
						"method": "POST",
						"header": [],
						"body": {
							"mode": "raw",
							"raw": "{\n\t\"email\": \"hekrhekr8@gmail.com\",\n\t\"password\": \"12345moa\"\n\n\t\n}",
							"options": {
								"raw": {
									"language": "json"
								}
							}
						},
						"url": {
							"raw": "{{url}}/users/login",
							"host": [
								"{{url}}"
							],
							"path": [
								"users",
								"login"
							]
						}
					},
					"response": []
				},
				{
					"name": "Profile",
					"request": {
						"method": "GET",
						"header": [],
						"url": {
							"raw": "{{url}}/users/me",
							"host": [
								"{{url}}"
							],
							"path": [
								"users",
								"me"
							]
						}
					},
					"response": []
				},
				{
					"name": "Log Out",
					"request": {
						"method": "POST",
						"header": [],
						"url": {
							"raw": "{{url}}/users/logout",
							"host": [
								"{{url}}"
							],
							"path": [
								"users",
								"logout"
							]
						}
					},
					"response": []
				},
				{
					"name": "Log Out All",
					"request": {
						"method": "POST",
						"header": [],
						"url": {
							"raw": "{{url}}/users/logoutall",
							"host": [
								"{{url}}"
							],
							"path": [
								"users",
								"logoutall"
							]
						}
					},
					"response": []
				},
				{
					"name": "Delete Profile",
					"request": {
						"method": "DELETE",
						"header": [],
						"url": {
							"raw": "{{url}}/users/me",
							"host": [
								"{{url}}"
							],
							"path": [
								"users",
								"me"
							]
						}
					},
					"response": []
				},
				{
					"name": "Update Profile",
					"request": {
						"method": "PATCH",
						"header": [],
						"body": {
							"mode": "raw",
							"raw": "{\n\t\"firstName\": \"Moatasem\",\n\t\"lastName\": \"Salama\",\n\t\"email\": \"newMoa@yahoo.com\",\n\t\"password\": \"moa12345\"\n\n\t\n}",
							"options": {
								"raw": {
									"language": "json"
								}
							}
						},
						"url": {
							"raw": "{{url}}/users/me",
							"host": [
								"{{url}}"
							],
							"path": [
								"users",
								"me"
							]
						}
					},
					"response": []
				},
				{
					"name": "Delete Profile-Picture",
					"request": {
						"method": "DELETE",
						"header": [],
						"url": {
							"raw": "{{url}}/users/me/avatar",
							"host": [
								"{{url}}"
							],
							"path": [
								"users",
								"me",
								"avatar"
							]
						}
					},
					"response": []
				}
			],
			"protocolProfileBehavior": {}
		}
	],
	"auth": {
		"type": "bearer",
		"bearer": [
			{
				"key": "token",
				"value": "{{authToken}}",
				"type": "string"
			}
		]
	},
	"event": [
		{
			"listen": "prerequest",
			"script": {
				"id": "7ce2dbd1-ce06-431d-9974-07fb2c10169d",
				"type": "text/javascript",
				"exec": [
					""
				]
			}
		},
		{
			"listen": "test",
			"script": {
				"id": "f53421a3-91be-43a4-8859-7177e44774e1",
				"type": "text/javascript",
				"exec": [
					""
				]
			}
		}
	],
	"protocolProfileBehavior": {}
}